{
    "물의 원소 가루": "water_elemental_powder",
    "물의 원소 조각": "water_elemental_shard",
    "물의 원소 정수": "water_elemental_essence",
    "진주": "pearl",
    "행운의 편지": "lucky_letter",
    "해적의 보물상자": "pirate_treasure_box",
    "마녀의 눈물": "witch_tear",
    "용왕의 왕관": "dragon_king_crown",
    "실종된 잠수부 헬멧": "missing_diver_helmet",
    "고대 물의 영혼석": "ancient_water_soulstone",
    "물의 정령의 유리구두": "water_spirit_glass_slipper",
    "땅의 원소 가루": "earth_elemental_powder",
    "땅의 원소 조각": "earth_elemental_shard",
    "땅의 원소 정수": "earth_elemental_essence",
    "가넷": "garnet",
    "아쿠아마린": "aquamarine",
    "토파즈": "topaz",
    "페리도트": "peridot",
    "솔라이트 원석": "solite_ore",
    "실종된 광부의 표본샘플": "missing_miner_sample",
    "고대의 피라미드 큐브": "ancient_pyramid_cube",
    "대지의 정령의 호박화석": "earth_spirit_amber_fossil",
    "불의 원소 가루": "fire_elemental_powder",
    "불의 원소 조각": "fire_elemental_shard",
    "불의 원소 정수": "fire_elemental_essence",
    "애벌레": "larva",
    "무당벌레": "ladybug",
    "메뚜기": "grasshopper",
    "딱정벌레": "beetle",
    "밀 번들": "wheat_bundle",
    "대나무 번들": "bamboo_bundle",
    "비트 번들": "beet_bundle",
    "감자 번들": "potato_bundle",
    "갈색 버섯 번들": "brown_mushroom_bundle",
    "빨간 버섯 번들": "red_mushroom_bundle",
    "선인장 번들": "cactus_bundle",
    "당근 번들": "carrot_bundle",
    "후렴화 번들": "chorus_flower_bundle",
    "코코아콩 번들": "cocoa_beans_bundle",
    "네더와트 번들": "nether_wart_bundle",
    "사탕수수 번들": "sugar_cane_bundle",
    "켈프 번들": "kelp_bundle",
    "수박 조각 번들": "melon_slice_bundle",
    "달콤한 열매 번들": "sweet_berries_bundle",
    "개량된 목화솜": "improved_cotton",
    "실종된 농부의 땅문서": "missing_farmer_deed",
    "고대식물의 모종": "ancient_plant_seedling",
    "불의 정령의 꽃 화관": "fire_spirit_flower_crown",
    "바람의 원소 가루": "wind_elemental_powder",
    "바람의 원소 조각": "wind_elemental_shard",
    "바람의 원소 정수": "wind_elemental_essence",
    "나무껍질": "tree_bark",
    "고목나무 수액": "old_tree_sap",
    "맨드레이크": "mandrake",
    "바오밥나무 뿌리": "baobab_root",
    "원시부족 가면": "primitive_tribe_mask",
    "실종된 나무꾼의 장갑": "missing_logger_gloves",
    "고대 정령의 메아리": "ancient_spirit_echo",
    "나무의 정령의 연꽃 찻잔": "tree_spirit_lotus_teacup",
    "영혼의 원소 가루": "soul_elemental_powder",
    "영혼의 원소 조각": "soul_elemental_shard",
    "영혼의 원소 정수": "soul_elemental_essence",
    "짐승의 송곳니": "beast_fang",
    "짐승의 가죽": "beast_hide",
    "짐승의 꼬리": "beast_tail",
    "독침": "poison_sting",
    "용의 피": "dragon_blood",
    "대지의 결정체": "earth_crystal",
    "부드러운 깃털": "soft_feather",
    "부드러운 털": "soft_fur",
    "버섯 고기": "mushroom_meat",
    "바람의 결정체": "wind_crystal",
    "물방울의 별": "waterdrop_star",
    "공허의 파동": "void_wave",
    "돌고래의 마음": "dolphin_heart",
    "물의 결정체": "water_crystal",
    "넘실거리는 불꽃": "waving_flame",
    "가스트의 파편": "ghast_fragment",
    "불의 결정체": "fire_crystal",
    "더러운 천": "dirty_cloth",
    "엔더 진주 가루": "ender_pearl_powder",
    "사악한 기운": "evil_aura",
    "수상한 주머니": "suspicious_pouch",
    "타락한 월계수 잎": "corrupted_laurel_leaf",
    "타락한 요정의 가루": "corrupted_fairy_powder",
    "어둠의 결정체": "dark_crystal",
    "미스틱 코어": "mystic_core",
    "갈비뼈": "rib_bone",
    "요정의 가루": "fairy_powder",
    "빛의 결정체": "light_crystal",
    "신비한 동물 가죽": "mystical_animal_hide",
    "실종된 사냥꾼 고글": "missing_hunter_goggles",
    "고대 맘모스 뿔": "ancient_mammoth_horn",
    "어둠의 정령의 부러진 스태프": "dark_spirit_broken_staff",

    "못": "nail",
    "기본 접착제": "build_glue",
    "철 주괴": "iron",
    "구리 주괴": "copper",

    "레드스톤 가루": "redstone",
    "슬라임 블록": "slime_block",
    "꿀 블록": "honey_block",
    "물병": "water_bottle",

    "곰백토": "dirt_dough",
    "거친 종이": "crumpled_paper",
    "반짝수": "mystery_water",
    "베어 강력 접착제": "super_glue",

    "연마 가루": "crafting_dust",
    "베어 크리스탈": "glass_orb",
    "탐욕의 실": "skein",
    "에너지 오브": "radiant_gear_essence",
    "요리용 그릇": "don_dish",
    "디저트용 그릇": "dessert_dish",
    "음료병": "empty_bottle",
    "공예품 끌": "chisel",

    "고품질 종이": "high_quality_paper",
    "고품질 원단": "high_quality_fabric",
    "정화 플라스크": "holy_flask",
    "정화의 결정": "purifying_crystal",
    "보존 코어 소자": "bipolar_chip",
    "보존 코어 모듈": "bipolar_module",
    "체인": "accessory_chain",
    "베어 철판": "smelted_iron_plate",
    "영혼 가죽": "groomed_leather",
    "무두질된 영혼 가죽": "high_grade_leather",

    "드래곤 마법진": "dragon_rune",
    "곤충 채집통": "bug_tong",
    "위더 크루세이더의 갑옷": "wither_crusader_armor",
    "맹독의 손길": "poison_glove",
    "여의주": "dragons_core",

    "미약한 불의 파편": "rune_fire_1",
    "불의 파편": "rune_fire_2",
    "농축된 불의 파편": "rune_fire_3",
    "미약한 바람의 파편": "rune_air_1",
    "바람의 파편": "rune_air_2",
    "농축된 바람의 파편": "rune_air_3",
    "미약한 물의 파편": "rune_water_1",
    "물의 파편": "rune_water_2",
    "농축된 물의 파편": "rune_water_3",
    "미약한 땅의 파편": "rune_earth_1",
    "땅의 파편": "rune_earth_2",
    "농축된 땅의 파편": "rune_earth_3",
    "미약한 영혼의 파편": "rune_soul_1",
    "영혼의 파편": "rune_soul_2",
    "농축된 영혼의 파편": "rune_soul_3",
    
    "벌레잡이 풀": "invicon_plant",
    "스니퍼 알": "sniffer_egg",
    "맹그로브 주아": "mangrove_propagule",
    "작은 흘림잎": "small_dripleaf",
    "앵무조개 껍데기": "nautilus_shell",
    "전달체": "conduit",
    "작은 자수정 봉우리": "small_amethyst",
    "큰 자수정 봉우리": "large_amethyst",
    "야생 사냥꾼 증표 I": "encounter1",
    "야생 사냥꾼 증표 II": "encounter2",
    "야생 사냥꾼 증표 III": "encounter3",

    "광부의 작은 지식": "earth_book",
    "농부의 작은 지식": "fire_book",
    "나무꾼의 작은 지식": "wind_book",
    "어부의 작은 지식": "water_book",
    "사냥꾼의 작은 지식": "soul_book",
    "대지의 보주": "earth_1",
    "불의 보주": "fire_1",
    "바람의 보주": "wind_1",
    "물의 보주": "water_1",
    "영혼의 보주": "soul_1",
    
    "쓸만한 대지의 병": "pot",
    "쓸만한 해바라기 조화": "sunflower",
    "쓸만한 바람의 시야": "binocular",
    "쓸만한 닻의 물결": "anchor",
    "쓸만한 사마귀의 손길": "mantis",
    "대지의 병": "pot",
    "해바라기 조화": "sunflower",
    "바람의 시야": "binocular",
    "닻의 물결": "anchor",
    "사마귀의 손길": "mantis",

    "일반 장비 가루": "common_dust",
    "고급 장비 가루": "uncommon_dust",
    "희귀 장비 가루": "rare_dust",
    "영웅 장비 가루": "epic_dust"


}